LICENSE.txt
MANIFEST.in
README.md
README.rst
setup.py
django_fileman.egg-info/PKG-INFO
django_fileman.egg-info/SOURCES.txt
django_fileman.egg-info/dependency_links.txt
django_fileman.egg-info/not-zip-safe
django_fileman.egg-info/requires.txt
django_fileman.egg-info/top_level.txt
fileman/__init__.py
fileman/_version.py
fileman/admin.py
fileman/apps.py
fileman/forms.py
fileman/views.py
fileman/static/fileman/fileman.css
fileman/static/fileman/fileman.css.map
fileman/static/fileman/fileman.js
fileman/static/fileman/fileman.scss
fileman/templates/fileman/add_directory.html
fileman/templates/fileman/base.html
fileman/templates/fileman/delete.html
fileman/templates/fileman/index.html
fileman/templates/fileman/rename.html
fileman/templates/fileman/static.html
fileman/templates/fileman/upload.html